nlpscaffold/__init__.py
nlpscaffold/dataset.py
nlpscaffold/model/__init__.py
nlpscaffold/model/base.py
nlpscaffold/utils/__init__.py
nlpscaffold/utils/prep.py
nlpscaffold/utils/tracker.py
nlpscaffold/utils/writer.py
nlpscaffold-0.0.1.dist-info/LICENSE
nlpscaffold-0.0.1.dist-info/METADATA
nlpscaffold-0.0.1.dist-info/WHEEL
nlpscaffold-0.0.1.dist-info/top_level.txt
nlpscaffold-0.0.1.dist-info/RECORD
